modelhub/__init__.py
modelhub/cli.py
modelhub/py.typed
modelhub/version.py
modelhub/clients/__init__.py
modelhub/clients/ai_gateway_client.py
modelhub/clients/dataset_client.py
modelhub/clients/inference_client.py
modelhub/clients/mlflow_client.py
modelhub/clients/pipeline_manager.py
modelhub/clients/prompts.py
modelhub/core/__init__.py
modelhub/datasets/__init__.py
modelhub/datasets/load_dataset.py
modelhub/evaluation/__init__.py
modelhub/evaluation/prompt_evaluator.py
modelhub/models/__init__.py
modelhub/models/inference.py
modelhub/models/model_card.py
modelhub/models/models.py
modelhub/models/prompts.py
modelhub/monitors/__init__.py
modelhub/monitors/factory.py
modelhub/monitors/llm_monitor.py
modelhub/monitors/ml_monitor.py
modelhub/monitors/interfaces/__init__.py
modelhub/monitors/interfaces/base_monitor.py
modelhub/monitors/interfaces/llm_monitor_interface.py
modelhub/monitors/interfaces/model_monitor_interface.py
modelhub/monitors/providers/__init__.py
modelhub/monitors/providers/evidently/__init__.py
modelhub/monitors/providers/evidently/evidently_llm_monitor.py
modelhub/monitors/providers/evidently/evidently_ml_monitor.py
modelhub/patches/__init__.py
modelhub/patches/mlflow/__init__.py
modelhub/patches/mlflow/google_cloud_storage.py
modelhub/serving/__init__.py
modelhub/serving/async_utils.py
modelhub/serving/base.py
modelhub/serving/inference_types.py
modelhub/serving/model_service.py
modelhub/serving/pdf_utils.py
modelhub/serving/protocol.py
modelhub/serving/server.py
modelhub/utils/__init__.py
modelhub/utils/encoder.py
autonomize_model_sdk-1.1.73.dist-info/METADATA
autonomize_model_sdk-1.1.73.dist-info/WHEEL
autonomize_model_sdk-1.1.73.dist-info/entry_points.txt
autonomize_model_sdk-1.1.73.dist-info/licenses/LICENSE
autonomize_model_sdk-1.1.73.dist-info/RECORD
