Metadata-Version: 2.4
Name: autonomize-model-sdk
Version: 1.1.73
Summary: SDK for creating and managing machine learning pipelines.
Author-email: Jagveer Singh <jagveer@autonomize.ai>
License: Proprietary
License-File: LICENSE
Keywords: inference,machine learning,mlflow,modelhub,sdk
Classifier: Intended Audience :: Developers
Classifier: License :: Other/Proprietary License
Classifier: Programming Language :: Python :: 3
Classifier: Programming Language :: Python :: 3.12
Requires-Python: <3.13,>=3.12
Requires-Dist: autonomize-core==0.1.16
Requires-Dist: datasets<4.0.0,>=3.2.0
Requires-Dist: httpx>=0.28.1
Requires-Dist: pydantic<3.0.0,>=2.10.6
Requires-Dist: python-dotenv<2.0.0,>=1.0.1
Requires-Dist: pyyaml<7.0,>=6.0
Requires-Dist: requests<3.0.0,>=2.32.2
Provides-Extra: aiohttp
Requires-Dist: aiohttp<4.0.0,>=3.8.3; extra == 'aiohttp'
Provides-Extra: albumentations
Requires-Dist: albumentations<2.0.0,>=1.3.1; extra == 'albumentations'
Provides-Extra: azure-deps
Requires-Dist: azure-identity; extra == 'azure-deps'
Requires-Dist: azure-storage-blob; extra == 'azure-deps'
Provides-Extra: azure-identity
Requires-Dist: azure-identity<2.0.0,>=1.12.0; extra == 'azure-identity'
Provides-Extra: azure-storage-blob
Requires-Dist: azure-storage-blob<13.0.0,>=12.14.2; extra == 'azure-storage-blob'
Provides-Extra: base
Requires-Dist: pandas; extra == 'base'
Provides-Extra: cloudpickle
Requires-Dist: cloudpickle<3.0.0,>=2.2.1; extra == 'cloudpickle'
Provides-Extra: core
Requires-Dist: base; extra == 'core'
Requires-Dist: datasets; extra == 'core'
Requires-Dist: mlflow; extra == 'core'
Requires-Dist: monitoring; extra == 'core'
Requires-Dist: pipeline; extra == 'core'
Provides-Extra: data-science
Requires-Dist: base; extra == 'data-science'
Requires-Dist: datasets; extra == 'data-science'
Requires-Dist: mlflow; extra == 'data-science'
Requires-Dist: monitoring; extra == 'data-science'
Provides-Extra: datasets
Requires-Dist: datasets; extra == 'datasets'
Requires-Dist: pandas; extra == 'datasets'
Provides-Extra: deployment
Requires-Dist: aiohttp; extra == 'deployment'
Requires-Dist: cloudpickle; extra == 'deployment'
Requires-Dist: evidently; extra == 'deployment'
Requires-Dist: ipython; extra == 'deployment'
Requires-Dist: kubernetes; extra == 'deployment'
Requires-Dist: pandas; extra == 'deployment'
Requires-Dist: pillow; extra == 'deployment'
Requires-Dist: platformdirs; extra == 'deployment'
Requires-Dist: python-multipart; extra == 'deployment'
Provides-Extra: evidently
Requires-Dist: evidently<0.8.0,>=0.7.9; extra == 'evidently'
Provides-Extra: genesis-flow
Requires-Dist: genesis-flow<2.0.0,>=1.0.9; extra == 'genesis-flow'
Provides-Extra: graphviz
Requires-Dist: graphviz<0.21.0,>=0.20.1; extra == 'graphviz'
Provides-Extra: image-serving
Requires-Dist: aiohttp; extra == 'image-serving'
Requires-Dist: cloudpickle; extra == 'image-serving'
Requires-Dist: pillow; extra == 'image-serving'
Requires-Dist: pymupdf; extra == 'image-serving'
Requires-Dist: python-multipart; extra == 'image-serving'
Provides-Extra: ipython
Requires-Dist: ipython<9.0.0,>=8.12.0; extra == 'ipython'
Provides-Extra: jinja2
Requires-Dist: jinja2<4.0.0,>=3.1.2; extra == 'jinja2'
Provides-Extra: kubernetes
Requires-Dist: kubernetes<33.0.0,>=32.0.0; extra == 'kubernetes'
Provides-Extra: mlflow
Requires-Dist: genesis-flow; extra == 'mlflow'
Requires-Dist: ipython; extra == 'mlflow'
Requires-Dist: jinja2; extra == 'mlflow'
Requires-Dist: pandas; extra == 'mlflow'
Provides-Extra: monitoring
Requires-Dist: evidently; extra == 'monitoring'
Requires-Dist: ipython; extra == 'monitoring'
Requires-Dist: pandas; extra == 'monitoring'
Requires-Dist: platformdirs; extra == 'monitoring'
Provides-Extra: networkx
Requires-Dist: networkx<3.0.0,>=2.8.8; extra == 'networkx'
Provides-Extra: pandas
Requires-Dist: pandas<3.0.0,>=2.2.3; extra == 'pandas'
Provides-Extra: pillow
Requires-Dist: pillow<11.0.0,>=10.2.0; extra == 'pillow'
Provides-Extra: pipeline
Requires-Dist: graphviz; extra == 'pipeline'
Requires-Dist: jinja2; extra == 'pipeline'
Requires-Dist: kubernetes; extra == 'pipeline'
Requires-Dist: networkx; extra == 'pipeline'
Requires-Dist: pandas; extra == 'pipeline'
Provides-Extra: platformdirs
Requires-Dist: platformdirs<5.0.0,>=4.3.6; extra == 'platformdirs'
Provides-Extra: pymupdf
Requires-Dist: pymupdf<2.0.0,>=1.23.5; extra == 'pymupdf'
Provides-Extra: pytest-asyncio
Requires-Dist: pytest-asyncio<0.26.0,>=0.25.3; extra == 'pytest-asyncio'
Provides-Extra: python-multipart
Requires-Dist: python-multipart<0.1.0,>=0.0.20; extra == 'python-multipart'
Provides-Extra: sentence-transformers
Requires-Dist: sentence-transformers<4.0.0,>=3.0.1; extra == 'sentence-transformers'
Provides-Extra: sentencepiece
Requires-Dist: sentencepiece<0.3.0,>=0.2.0; extra == 'sentencepiece'
Provides-Extra: serving
Requires-Dist: aiohttp; extra == 'serving'
Requires-Dist: cloudpickle; extra == 'serving'
Requires-Dist: pillow; extra == 'serving'
Requires-Dist: python-multipart; extra == 'serving'
Provides-Extra: text-serving
Requires-Dist: aiohttp; extra == 'text-serving'
Requires-Dist: cloudpickle; extra == 'text-serving'
Requires-Dist: pillow; extra == 'text-serving'
Requires-Dist: python-multipart; extra == 'text-serving'
Requires-Dist: sentencepiece; extra == 'text-serving'
Requires-Dist: transformers; extra == 'text-serving'
Provides-Extra: timm
Requires-Dist: timm<0.6.0,>=0.5.4; extra == 'timm'
Provides-Extra: torch
Requires-Dist: torch<3.0.0,>=2.0.1; extra == 'torch'
Provides-Extra: torchvision
Requires-Dist: torchvision<0.21.0,>=0.20.1; extra == 'torchvision'
Provides-Extra: transformers
Requires-Dist: transformers<5.0.0,>=4.25.1; extra == 'transformers'
Provides-Extra: vision-models
Requires-Dist: aiohttp; extra == 'vision-models'
Requires-Dist: albumentations; extra == 'vision-models'
Requires-Dist: cloudpickle; extra == 'vision-models'
Requires-Dist: pillow; extra == 'vision-models'
Requires-Dist: pymupdf; extra == 'vision-models'
Requires-Dist: python-multipart; extra == 'vision-models'
Requires-Dist: timm; extra == 'vision-models'
Requires-Dist: torch; extra == 'vision-models'
Requires-Dist: torchvision; extra == 'vision-models'
